pynumeric/__init__.py
pynumeric-0.1.2.dist-info/DESCRIPTION.rst
pynumeric-0.1.2.dist-info/METADATA
pynumeric-0.1.2.dist-info/RECORD
pynumeric-0.1.2.dist-info/WHEEL
pynumeric-0.1.2.dist-info/entry_points.txt
pynumeric-0.1.2.dist-info/metadata.json
pynumeric-0.1.2.dist-info/top_level.txt
