Metadata-Version: 2.0
Name: pynumeric
Version: 0.1.2
Summary: pynumeric is a Python package to read MSC Radar Numeric data
Home-page: https://github.com/ECCC-MSC/pynumeric.git
Author: Meteorological Service of Canada
Author-email: tom.kralidis@canada.ca
License: GPLv3
Keywords: numeric radar msc
Platform: all
Classifier: Development Status :: 4 - Beta
Classifier: Environment :: Console
Classifier: Intended Audience :: Developers
Classifier: Intended Audience :: Science/Research
Classifier: License :: OSI Approved :: GNU General Public License v3 (GPLv3)
Classifier: Operating System :: OS Independent
Classifier: Programming Language :: Python
Requires-Dist: click
Requires-Dist: six
